boardwalk/__init__.py
boardwalk/boardwalk.py
boardwalk-0.0.1.dist-info/LICENSE
boardwalk-0.0.1.dist-info/METADATA
boardwalk-0.0.1.dist-info/WHEEL
boardwalk-0.0.1.dist-info/top_level.txt
boardwalk-0.0.1.dist-info/RECORD
